odoo/addons/module_auto_update/README.rst
odoo/addons/module_auto_update/__init__.py
odoo/addons/module_auto_update/__manifest__.py
odoo/addons/module_auto_update/addon_hash.py
odoo/addons/module_auto_update/hooks.py
odoo/addons/module_auto_update/i18n/ca.po
odoo/addons/module_auto_update/i18n/cs_CZ.po
odoo/addons/module_auto_update/i18n/de.po
odoo/addons/module_auto_update/i18n/es.po
odoo/addons/module_auto_update/i18n/es_AR.po
odoo/addons/module_auto_update/i18n/es_MX.po
odoo/addons/module_auto_update/i18n/fr.po
odoo/addons/module_auto_update/i18n/hr.po
odoo/addons/module_auto_update/i18n/it.po
odoo/addons/module_auto_update/i18n/module_auto_update.pot
odoo/addons/module_auto_update/i18n/nl_NL.po
odoo/addons/module_auto_update/i18n/pt_BR.po
odoo/addons/module_auto_update/i18n/sl.po
odoo/addons/module_auto_update/i18n/tr.po
odoo/addons/module_auto_update/i18n/zh_CN.po
odoo/addons/module_auto_update/models/__init__.py
odoo/addons/module_auto_update/models/module.py
odoo/addons/module_auto_update/readme/CONFIGURE.md
odoo/addons/module_auto_update/readme/CONTRIBUTORS.md
odoo/addons/module_auto_update/readme/DESCRIPTION.md
odoo/addons/module_auto_update/readme/USAGE.md
odoo/addons/module_auto_update/static/description/icon.png
odoo/addons/module_auto_update/static/description/index.html
odoo/addons/module_auto_update/tests/__init__.py
odoo/addons/module_auto_update/tests/test_addon_hash.py
odoo/addons/module_auto_update/tests/test_module.py
odoo/addons/module_auto_update/tests/sample_module/README.rst
odoo/addons/module_auto_update/tests/sample_module/data/f1.xml
odoo/addons/module_auto_update/tests/sample_module/data/f2.xml
odoo/addons/module_auto_update/tests/sample_module/i18n/en_US.po
odoo/addons/module_auto_update/tests/sample_module/i18n/fr.po
odoo/addons/module_auto_update/tests/sample_module/i18n/fr_BE.po
odoo/addons/module_auto_update/tests/sample_module/i18n/test.pot
odoo/addons/module_auto_update/tests/sample_module/i18n_extra/en.po
odoo_addon_module_auto_update-18.0.1.0.0.4.dist-info/METADATA
odoo_addon_module_auto_update-18.0.1.0.0.4.dist-info/WHEEL
odoo_addon_module_auto_update-18.0.1.0.0.4.dist-info/top_level.txt
odoo_addon_module_auto_update-18.0.1.0.0.4.dist-info/RECORD
