Metadata-Version: 2.1
Name: odoo-addon-module_auto_update
Version: 18.0.1.0.0.4
Requires-Python: >=3.10
Requires-Dist: odoo==18.0.*
Summary: Automatically update Odoo modules
Home-page: https://github.com/OCA/server-tools
License: LGPL-3
Author: =?utf-8?q?LasLabs=2C_Juan_Jos=C3=A9_Scaraf=C3=ADa=2C_Tecnativa=2C_ACSONE_SA/NV=2C_Odoo_Community_Association_=28OCA=29?=
Author-email: support@odoo-community.org
Classifier: Programming Language :: Python
Classifier: Framework :: Odoo
Classifier: Framework :: Odoo :: 18.0
Classifier: License :: OSI Approved :: GNU Lesser General Public License v3 (LGPLv3)
Classifier: Development Status :: 5 - Production/Stable
